{
    "Tuning metric": "f1-macro",
    "Best_scores": {
        "SVM": 0.7357371794871794,
        "Random Forest": 0.733044761962018,
        "LightGBM": 0.7289763769051152,
        "kNN": 0.7027374536151842,
        "Logistic Regression": 0.7249331193151418,
        "Gaussian Naive Bayes": 0.5161692576274005
    },
    "Best_params": {
        "SVM": {
            "C": 1,
            "kernel": "linear"
        },
        "Random Forest": {
            "bootstrap": true,
            "max_depth": 24,
            "max_features": "auto",
            "min_samples_leaf": 1,
            "min_samples_split": 20,
            "n_estimators": 100
        },
        "LightGBM": {},
        "kNN": {
            "metric": "minkowski",
            "n_neighbors": 15,
            "weights": "uniform"
        },
        "Logistic Regression": {
            "max_iter": 100
        },
        "Gaussian Naive Bayes": {}
    }
}